{"is_source_file": true, "format": "TypeScript (Angular module)", "description": "This file defines the main application module for an Angular frontend, configuring components, imports, and bootstrap information.", "external_files": ["./app.component", "./layout/header.component", "./layout/sidebar.component", "./notes/notes.component", "./notes/note-editor.component", "./notes/notes-list.component"], "external_methods": ["NgModule"], "published": ["AppModule"], "classes": [{"name": "AppModule", "description": "Main application module that declares components, imports necessary modules, and specifies the bootstrap component."}], "methods": [], "calls": ["NgModule", "BrowserModule", "HttpClientModule", "FormsModule"], "search-terms": ["Angular", "NgModule", "app.module.ts", "NotesComponent", "NoteEditorComponent", "NotesListComponent"], "state": 2, "file_id": 21, "knowledge_revision": 46, "git_revision": "", "ctags": [{"_type": "tag", "name": "AppModule", "path": "/home/kavia/workspace/code-generation/note-organizer-155227-155236/notes_frontend/src/app/app.module.ts", "pattern": "/^export class AppModule { }$/", "language": "TypeScript", "kind": "class"}], "hash": "77715e4cf706b85ed41f2e3eee3f3ed9", "format-version": 4, "code-base-name": "notes_frontend", "filename": "notes_frontend/src/app/app.module.ts", "revision_history": [{"46": ""}]}